odoo10_addon_product_default_image-10.0.1.0.0-py2.7-nspkg.pth
odoo/addons/product_default_image/README.rst
odoo/addons/product_default_image/__init__.py
odoo/addons/product_default_image/__manifest__.py
odoo/addons/product_default_image/hooks.py
odoo/addons/product_default_image/image_constants.py
odoo/addons/product_default_image/demo/product_category_demo.xml
odoo/addons/product_default_image/demo/product_template_demo.xml
odoo/addons/product_default_image/demo/res_company_demo.xml
odoo/addons/product_default_image/models/__init__.py
odoo/addons/product_default_image/models/abstract_product_image.py
odoo/addons/product_default_image/models/product_category.py
odoo/addons/product_default_image/models/product_template.py
odoo/addons/product_default_image/models/res_company.py
odoo/addons/product_default_image/models/stock_config_settings.py
odoo/addons/product_default_image/static/description/icon.png
odoo/addons/product_default_image/static/src/img/glob_prod_img.png
odoo/addons/product_default_image/tests/__init__.py
odoo/addons/product_default_image/tests/setup.py
odoo/addons/product_default_image/tests/test_abstract_product_image.py
odoo/addons/product_default_image/tests/test_hooks.py
odoo/addons/product_default_image/tests/test_product_category.py
odoo/addons/product_default_image/tests/test_product_template.py
odoo/addons/product_default_image/tests/test_res_company.py
odoo/addons/product_default_image/views/product_category_view.xml
odoo/addons/product_default_image/views/product_template_view.xml
odoo/addons/product_default_image/views/stock_config_settings_view.xml
odoo10_addon_product_default_image-10.0.1.0.0.dist-info/DESCRIPTION.rst
odoo10_addon_product_default_image-10.0.1.0.0.dist-info/METADATA
odoo10_addon_product_default_image-10.0.1.0.0.dist-info/RECORD
odoo10_addon_product_default_image-10.0.1.0.0.dist-info/WHEEL
odoo10_addon_product_default_image-10.0.1.0.0.dist-info/metadata.json
odoo10_addon_product_default_image-10.0.1.0.0.dist-info/namespace_packages.txt
odoo10_addon_product_default_image-10.0.1.0.0.dist-info/top_level.txt
